Metadata-Version: 2.1
Name: formatinger
Version: 0.1
Summary: Converts phone numbers and postal addresses into a more pleasant or hidden look.
Home-page: UNKNOWN
Author-email: beeeirym@gmail.com
License: UNKNOWN
Platform: UNKNOWN
